{
    "project_name": "",
    "project_key": "{{cookiecutter.project_name|lower|replace('-', '')|replace('_', '')}}",
    "package": "dev.mbo.{{cookiecutter.project_key}}",
    "package_dir": "{{cookiecutter.package|replace('.', '/')}}",
    "version": "0.0.1-SNAPSHOT",
    "java_version": "21",
    "api_port": "8080",
    "version_control": [
        "git",
        "none"
    ],
    "_copy_without_render": [
        "*.jar",
        "gradlew",
        "gradlew.bat",
        "*.mustache",
        "*.http"
    ]
}